<!-- This XML file has been created by Easy Java(script) Simulations (EjsS). Visit http://www.um.es/fem/Ejs. -->
<!-- Please, save the file to your hard disk on your Ejs' user directory and open it with Ejs. -->
<Osejs version="5.1" password="">
<Osejs.Information>
<Title><![CDATA[Light Intensity simulation]]></Title>
<Copyright><![CDATA[Creative Commons Attribution]]></Copyright>
<Keywords><![CDATA[]]></Keywords>
<Password><![CDATA[]]></Password>
<Level><![CDATA[]]></Level>
<Language><![CDATA[]]></Language>
<Abstract><![CDATA[]]></Abstract>
<ExecPassword><![CDATA[]]></ExecPassword>
<CaptureTools>true</CaptureTools>
<DataTools>true</DataTools>
<LanguageTools>true</LanguageTools>
<AppletColSupport>false</AppletColSupport>
<UseMacMenuBar>false</UseMacMenuBar>
<RunInBrowserFirst>false</RunInBrowserFirst>
<UseInterpreter>true</UseInterpreter>
<UseDeltaForODE>false</UseDeltaForODE>
<ModelTab></ModelTab>
<ModelTabTitle><![CDATA[]]></ModelTabTitle>
<ModelName><![CDATA[]]></ModelName>
<MenuPosition>0</MenuPosition>
<CSSFolder></CSSFolder>
<Logo>./Light intensity/intensity.png</Logo>
<Author><![CDATA[Loo Kang Wee (weelookang@gmail.com)]]></Author>
<AuthorLogo>./Light intensity/lookangphoto.png</AuthorLogo>
<AdditionalLibraries>
</AdditionalLibraries>
<ImportStatements>
</ImportStatements>
<ClassesRequired>
</ClassesRequired>
<ManifestLines><![CDATA[Permissions: sandbox
Codebase: *
Caller-Allowable-Codebase: *
]]></ManifestLines>
<DetectedFiles><![CDATA[./Light intensity/intensity.png;./Light intensity/lookangphoto.png;]]></DetectedFiles>
<AuxiliaryFiles><![CDATA[./Light intensity/;]]></AuxiliaryFiles>
</Osejs.Information>
<Osejs.Description>
<Osejs.Description.Page>
<Type>DESCRIPTION_EDITOR</Type>
<Name>Intro Page</Name>
<Active>true</Active>
<Internal>false</Internal>
<Content>
<OneHTMLPage>
  <Locale>_default_</Locale>
  <Title>Intro Page</Title>
  <External>false</External>
  <![CDATA[
<html>
  <head>
    <style type="text/css">
      <!--
        ï»¿ body { margin-left: 3%; margin-right: 3%; margin-top: 2%; margin-bottom: 5%; text-align: justify; font-size: medium }
        h1 { text-indent: 0px; text-align: left; font-family: Helvetica, Geneva, Arial, SunSans-Regular, sans-serif; color: #0000C8; margin-top: 0; margin-right: 0; margin-bottom: 0; margin-left: 0; padding-top: 0; padding-right: 0; padding-bottom: 0; padding-left: 0; font-size: 135% !important }
        h2 { text-indent: 0px; text-align: left; font-family: Helvetica, Geneva, Arial, SunSans-Regular, sans-serif; color: #000777; font-size: 120% !important }
        h3 { text-indent: 0px; text-align: left; font-family: Helvetica, Geneva, Arial, SunSans-Regular, sans-serif; color: navy; font-size: 110% !important }
        h4 { text-indent: 0px; text-align: left; font-family: Helvetica, Geneva, Arial, SunSans-Regular, sans-serif }
        h5 { text-indent: 0px; text-align: left; font-family: Helvetica, Geneva, Arial, SunSans-Regular, sans-serif }
        h6 { text-indent: 0px; text-align: left; font-family: Helvetica, Geneva, Arial, SunSans-Regular, sans-serif }
        li { text-align: left; margin-top: 0; margin-bottom: 0 }
        p { font-family: Georgia, Times New Roman, Times, serif; line-height: 1.5em; margin-top: 0; margin-right: 0; margin-bottom: 0; margin-left: 0; text-align: justify }
        a:link { color: blue }
        a:visited { color: purple }
        address { margin-top: 0; padding-top: 0; border-top-color: border-color; border-top-style: dotted; border-top-width: thin }
        body { color: purple; font-family: Georgia, Times New Roman, Times, serif; background-color: #C8DFD0 }
      -->
    </style>
    
  </head>
  <body>
    Designed by Fu-Kwun Hwang <a href="http://www.phy.ntnu.edu.tw/ntnujava/">http://www.phy.ntnu.edu.tw/ntnujava/</a> 
    For more info: <a href="http://weelookang.blogspot.sg/2012/10/ejs-open-source-lens-with-light-path.html" cr="true">http://weelookang.blogspot.sg/2012/10/ejs-open-source-lens-with-light-path.html</a>
  </body>
</html>

]]>
</OneHTMLPage>
</Content>
</Osejs.Description.Page>
</Osejs.Description>
<Osejs.Model>
<Osejs.Model.FramesPerSecond>20</Osejs.Model.FramesPerSecond>
<Osejs.Model.StepsPerDisplay>1</Osejs.Model.StepsPerDisplay>
<Osejs.Model.RealTimeVariable></Osejs.Model.RealTimeVariable>
<Osejs.Model.Autostart>true</Osejs.Model.Autostart>
<Osejs.Model.Variables>
<Osejs.Model.Variables.Page>
<Type>VARIABLE_EDITOR</Type>
<Name>coordinate</Name>
<Active>true</Active>
<Internal>false</Internal>
<Content>
<PageComment><![CDATA[]]></PageComment>
<Variable>
<Name><![CDATA[range]]></Name>
<Value><![CDATA[200]]></Value>
<Type><![CDATA[double]]></Type>
<Dimension><![CDATA[]]></Dimension>
<Comment><![CDATA[½d³ò]]></Comment>
</Variable>
<Variable>
<Name><![CDATA[xmin]]></Name>
<Value><![CDATA[-range]]></Value>
<Type><![CDATA[double]]></Type>
<Dimension><![CDATA[]]></Dimension>
<Comment><![CDATA[x ·¥¤p]]></Comment>
</Variable>
<Variable>
<Name><![CDATA[xmax]]></Name>
<Value><![CDATA[range]]></Value>
<Type><![CDATA[double]]></Type>
<Dimension><![CDATA[]]></Dimension>
<Comment><![CDATA[x·¥¤j]]></Comment>
</Variable>
<Variable>
<Name><![CDATA[ymin]]></Name>
<Value><![CDATA[-range/2]]></Value>
<Type><![CDATA[double]]></Type>
<Dimension><![CDATA[]]></Dimension>
<Comment><![CDATA[y·¥¤p]]></Comment>
</Variable>
<Variable>
<Name><![CDATA[ymax]]></Name>
<Value><![CDATA[range/2]]></Value>
<Type><![CDATA[double]]></Type>
<Dimension><![CDATA[]]></Dimension>
<Comment><![CDATA[y·¥¤j]]></Comment>
</Variable>
<Variable>
<Name><![CDATA[t]]></Name>
<Value><![CDATA[0.0]]></Value>
<Type><![CDATA[double]]></Type>
<Dimension><![CDATA[]]></Dimension>
<Comment><![CDATA[®É¶¡]]></Comment>
</Variable>
<Variable>
<Name><![CDATA[dt]]></Name>
<Value><![CDATA[0.05]]></Value>
<Type><![CDATA[double]]></Type>
<Dimension><![CDATA[]]></Dimension>
<Comment><![CDATA[®É¶¡¶¡¶Z]]></Comment>
</Variable>
<Variable>
<Name><![CDATA[size]]></Name>
<Value><![CDATA[range/40]]></Value>
<Type><![CDATA[double]]></Type>
<Dimension><![CDATA[]]></Dimension>
<Comment><![CDATA[²É¤lÅã¥Üªº¤j¤p]]></Comment>
</Variable>
<Variable>
<Name><![CDATA[size2]]></Name>
<Value><![CDATA[size/2.]]></Value>
<Type><![CDATA[double]]></Type>
<Dimension><![CDATA[]]></Dimension>
<Comment><![CDATA[]]></Comment>
</Variable>
<Variable>
<Name><![CDATA[size4]]></Name>
<Value><![CDATA[0.0]]></Value>
<Type><![CDATA[double]]></Type>
<Dimension><![CDATA[]]></Dimension>
<Comment><![CDATA[]]></Comment>
</Variable>
<Variable>
<Name><![CDATA[label]]></Name>
<Value><![CDATA["play"]]></Value>
<Type><![CDATA[String]]></Type>
<Dimension><![CDATA[]]></Dimension>
<Comment><![CDATA[]]></Comment>
</Variable>
<Variable>
<Name><![CDATA[zero]]></Name>
<Value><![CDATA[0.0]]></Value>
<Type><![CDATA[double]]></Type>
<Dimension><![CDATA[]]></Dimension>
<Comment><![CDATA[]]></Comment>
</Variable>
<Variable>
<Name><![CDATA[h]]></Name>
<Value><![CDATA[range/5]]></Value>
<Type><![CDATA[double]]></Type>
<Dimension><![CDATA[]]></Dimension>
<Comment><![CDATA[]]></Comment>
</Variable>
<Variable>
<Name><![CDATA[h2]]></Name>
<Value><![CDATA[0.1]]></Value>
<Type><![CDATA[double]]></Type>
<Dimension><![CDATA[]]></Dimension>
<Comment><![CDATA[]]></Comment>
</Variable>
<Variable>
<Name><![CDATA[stroke]]></Name>
<Value><![CDATA[3.0]]></Value>
<Type><![CDATA[double]]></Type>
<Dimension><![CDATA[]]></Dimension>
<Comment><![CDATA[]]></Comment>
</Variable>
<Variable>
<Name><![CDATA[]]></Name>
<Value><![CDATA[]]></Value>
<Type><![CDATA[double]]></Type>
<Dimension><![CDATA[]]></Dimension>
<Comment><![CDATA[]]></Comment>
</Variable>
</Content>
</Osejs.Model.Variables.Page>
<Osejs.Model.Variables.Page>
<Type>VARIABLE_EDITOR</Type>
<Name>language</Name>
<Active>true</Active>
<Internal>false</Internal>
<Content>
<PageComment><![CDATA[]]></PageComment>
<Variable>
<Name><![CDATA[l_play]]></Name>
<Value><![CDATA["play"]]></Value>
<Type><![CDATA[String]]></Type>
<Dimension><![CDATA[]]></Dimension>
<Comment><![CDATA[]]></Comment>
</Variable>
<Variable>
<Name><![CDATA[l_pause]]></Name>
<Value><![CDATA["pause"]]></Value>
<Type><![CDATA[String]]></Type>
<Dimension><![CDATA[]]></Dimension>
<Comment><![CDATA[]]></Comment>
</Variable>
<Variable>
<Name><![CDATA[l_reset]]></Name>
<Value><![CDATA["reset"]]></Value>
<Type><![CDATA[String]]></Type>
<Dimension><![CDATA[]]></Dimension>
<Comment><![CDATA[]]></Comment>
</Variable>
<Variable>
<Name><![CDATA[l_init]]></Name>
<Value><![CDATA["initialize"]]></Value>
<Type><![CDATA[String]]></Type>
<Dimension><![CDATA[]]></Dimension>
<Comment><![CDATA[]]></Comment>
</Variable>
<Variable>
<Name><![CDATA[l_msg]]></Name>
<Value><![CDATA["block part of light paths"]]></Value>
<Type><![CDATA[String]]></Type>
<Dimension><![CDATA[]]></Dimension>
<Comment><![CDATA[]]></Comment>
</Variable>
<Variable>
<Name><![CDATA[l_focus]]></Name>
<Value><![CDATA["Focus point"]]></Value>
<Type><![CDATA[String]]></Type>
<Dimension><![CDATA[]]></Dimension>
<Comment><![CDATA[]]></Comment>
</Variable>
<Variable>
<Name><![CDATA[l_autoy]]></Name>
<Value><![CDATA["show different light paths automatically"]]></Value>
<Type><![CDATA[String]]></Type>
<Dimension><![CDATA[]]></Dimension>
<Comment><![CDATA[]]></Comment>
</Variable>
<Variable>
<Name><![CDATA[I_intensity]]></Name>
<Value><![CDATA["Intensity"]]></Value>
<Type><![CDATA[String]]></Type>
<Dimension><![CDATA[]]></Dimension>
<Comment><![CDATA[]]></Comment>
</Variable>
<Variable>
<Name><![CDATA[]]></Name>
<Value><![CDATA[0.0]]></Value>
<Type><![CDATA[double]]></Type>
<Dimension><![CDATA[]]></Dimension>
<Comment><![CDATA[]]></Comment>
</Variable>
<Variable>
<Name><![CDATA[]]></Name>
<Value><![CDATA[]]></Value>
<Type><![CDATA[double]]></Type>
<Dimension><![CDATA[]]></Dimension>
<Comment><![CDATA[]]></Comment>
</Variable>
</Content>
</Osejs.Model.Variables.Page>
<Osejs.Model.Variables.Page>
<Type>VARIABLE_EDITOR</Type>
<Name>basic</Name>
<Active>true</Active>
<Internal>false</Internal>
<Content>
<PageComment><![CDATA[]]></PageComment>
<Variable>
<Name><![CDATA[x]]></Name>
<Value><![CDATA[0]]></Value>
<Type><![CDATA[double]]></Type>
<Dimension><![CDATA[]]></Dimension>
<Comment><![CDATA[]]></Comment>
</Variable>
<Variable>
<Name><![CDATA[y]]></Name>
<Value><![CDATA[0]]></Value>
<Type><![CDATA[double]]></Type>
<Dimension><![CDATA[]]></Dimension>
<Comment><![CDATA[]]></Comment>
</Variable>
<Variable>
<Name><![CDATA[f]]></Name>
<Value><![CDATA[range/4]]></Value>
<Type><![CDATA[double]]></Type>
<Dimension><![CDATA[]]></Dimension>
<Comment><![CDATA[focus length]]></Comment>
</Variable>
<Variable>
<Name><![CDATA[x1]]></Name>
<Value><![CDATA[x+f]]></Value>
<Type><![CDATA[double]]></Type>
<Dimension><![CDATA[]]></Dimension>
<Comment><![CDATA[focus point to the right]]></Comment>
</Variable>
<Variable>
<Name><![CDATA[x2]]></Name>
<Value><![CDATA[x-f]]></Value>
<Type><![CDATA[double]]></Type>
<Dimension><![CDATA[]]></Dimension>
<Comment><![CDATA[focus point to the left]]></Comment>
</Variable>
<Variable>
<Name><![CDATA[p]]></Name>
<Value><![CDATA[x-2*f]]></Value>
<Type><![CDATA[double]]></Type>
<Dimension><![CDATA[]]></Dimension>
<Comment><![CDATA[]]></Comment>
</Variable>
<Variable>
<Name><![CDATA[q]]></Name>
<Value><![CDATA[0.0]]></Value>
<Type><![CDATA[double]]></Type>
<Dimension><![CDATA[]]></Dimension>
<Comment><![CDATA[]]></Comment>
</Variable>
<Variable>
<Name><![CDATA[lh]]></Name>
<Value><![CDATA[range/2]]></Value>
<Type><![CDATA[double]]></Type>
<Dimension><![CDATA[]]></Dimension>
<Comment><![CDATA[lens height]]></Comment>
</Variable>
<Variable>
<Name><![CDATA[]]></Name>
<Value><![CDATA[]]></Value>
<Type><![CDATA[double]]></Type>
<Dimension><![CDATA[]]></Dimension>
<Comment><![CDATA[]]></Comment>
</Variable>
</Content>
</Osejs.Model.Variables.Page>
<Osejs.Model.Variables.Page>
<Type>VARIABLE_EDITOR</Type>
<Name>view</Name>
<Active>true</Active>
<Internal>false</Internal>
<Content>
<PageComment><![CDATA[]]></PageComment>
<Variable>
<Name><![CDATA[n]]></Name>
<Value><![CDATA[15]]></Value>
<Type><![CDATA[int]]></Type>
<Dimension><![CDATA[]]></Dimension>
<Comment><![CDATA[]]></Comment>
</Variable>
<Variable>
<Name><![CDATA[xp1]]></Name>
<Value><![CDATA[0.0]]></Value>
<Type><![CDATA[double]]></Type>
<Dimension><![CDATA[[n]]]></Dimension>
<Comment><![CDATA[]]></Comment>
</Variable>
<Variable>
<Name><![CDATA[yp1]]></Name>
<Value><![CDATA[0.0]]></Value>
<Type><![CDATA[double]]></Type>
<Dimension><![CDATA[[n]]]></Dimension>
<Comment><![CDATA[]]></Comment>
</Variable>
<Variable>
<Name><![CDATA[xp2]]></Name>
<Value><![CDATA[0.0]]></Value>
<Type><![CDATA[double]]></Type>
<Dimension><![CDATA[[n]]]></Dimension>
<Comment><![CDATA[]]></Comment>
</Variable>
<Variable>
<Name><![CDATA[yp2]]></Name>
<Value><![CDATA[0.0]]></Value>
<Type><![CDATA[double]]></Type>
<Dimension><![CDATA[[n]]]></Dimension>
<Comment><![CDATA[]]></Comment>
</Variable>
<Variable>
<Name><![CDATA[dxp1]]></Name>
<Value><![CDATA[]]></Value>
<Type><![CDATA[double]]></Type>
<Dimension><![CDATA[[n]]]></Dimension>
<Comment><![CDATA[]]></Comment>
</Variable>
<Variable>
<Name><![CDATA[dyp1]]></Name>
<Value><![CDATA[]]></Value>
<Type><![CDATA[double]]></Type>
<Dimension><![CDATA[[n]]]></Dimension>
<Comment><![CDATA[]]></Comment>
</Variable>
<Variable>
<Name><![CDATA[dxp2]]></Name>
<Value><![CDATA[0.0]]></Value>
<Type><![CDATA[double]]></Type>
<Dimension><![CDATA[[n]]]></Dimension>
<Comment><![CDATA[]]></Comment>
</Variable>
<Variable>
<Name><![CDATA[dyp2]]></Name>
<Value><![CDATA[0.0]]></Value>
<Type><![CDATA[double]]></Type>
<Dimension><![CDATA[[n]]]></Dimension>
<Comment><![CDATA[]]></Comment>
</Variable>
<Variable>
<Name><![CDATA[ly]]></Name>
<Value><![CDATA[h/2]]></Value>
<Type><![CDATA[double]]></Type>
<Dimension><![CDATA[]]></Dimension>
<Comment><![CDATA[]]></Comment>
</Variable>
<Variable>
<Name><![CDATA[vxp]]></Name>
<Value><![CDATA[0.0]]></Value>
<Type><![CDATA[double]]></Type>
<Dimension><![CDATA[]]></Dimension>
<Comment><![CDATA[]]></Comment>
</Variable>
<Variable>
<Name><![CDATA[vyp]]></Name>
<Value><![CDATA[0.0]]></Value>
<Type><![CDATA[double]]></Type>
<Dimension><![CDATA[]]></Dimension>
<Comment><![CDATA[]]></Comment>
</Variable>
<Variable>
<Name><![CDATA[block]]></Name>
<Value><![CDATA[-1]]></Value>
<Type><![CDATA[int]]></Type>
<Dimension><![CDATA[[n]]]></Dimension>
<Comment><![CDATA[-1, stage1 / 0: stage 2/ 1: block]]></Comment>
</Variable>
<Variable>
<Name><![CDATA[stage]]></Name>
<Value><![CDATA[0]]></Value>
<Type><![CDATA[int]]></Type>
<Dimension><![CDATA[[n]]]></Dimension>
<Comment><![CDATA[]]></Comment>
</Variable>
<Variable>
<Name><![CDATA[c]]></Name>
<Value><![CDATA[range]]></Value>
<Type><![CDATA[double]]></Type>
<Dimension><![CDATA[]]></Dimension>
<Comment><![CDATA[]]></Comment>
</Variable>
<Variable>
<Name><![CDATA[bx]]></Name>
<Value><![CDATA[x-size*2]]></Value>
<Type><![CDATA[double]]></Type>
<Dimension><![CDATA[]]></Dimension>
<Comment><![CDATA[]]></Comment>
</Variable>
<Variable>
<Name><![CDATA[bh]]></Name>
<Value><![CDATA[lh/2]]></Value>
<Type><![CDATA[double]]></Type>
<Dimension><![CDATA[]]></Dimension>
<Comment><![CDATA[]]></Comment>
</Variable>
<Variable>
<Name><![CDATA[clr]]></Name>
<Value><![CDATA[]]></Value>
<Type><![CDATA[Object]]></Type>
<Dimension><![CDATA[]]></Dimension>
<Comment><![CDATA[]]></Comment>
</Variable>
<Variable>
<Name><![CDATA[bcount]]></Name>
<Value><![CDATA[0]]></Value>
<Type><![CDATA[int]]></Type>
<Dimension><![CDATA[]]></Dimension>
<Comment><![CDATA[]]></Comment>
</Variable>
<Variable>
<Name><![CDATA[ldy]]></Name>
<Value><![CDATA[h/10]]></Value>
<Type><![CDATA[double]]></Type>
<Dimension><![CDATA[]]></Dimension>
<Comment><![CDATA[]]></Comment>
</Variable>
<Variable>
<Name><![CDATA[autoy]]></Name>
<Value><![CDATA[]]></Value>
<Type><![CDATA[boolean]]></Type>
<Dimension><![CDATA[]]></Dimension>
<Comment><![CDATA[]]></Comment>
</Variable>
<Variable>
<Name><![CDATA[blocked]]></Name>
<Value><![CDATA[false]]></Value>
<Type><![CDATA[boolean]]></Type>
<Dimension><![CDATA[]]></Dimension>
<Comment><![CDATA[]]></Comment>
</Variable>
<Variable>
<Name><![CDATA[Ivalue]]></Name>
<Value><![CDATA[0.0]]></Value>
<Type><![CDATA[double]]></Type>
<Dimension><![CDATA[]]></Dimension>
<Comment><![CDATA[]]></Comment>
</Variable>
<Variable>
<Name><![CDATA[Itext]]></Name>
<Value><![CDATA[""]]></Value>
<Type><![CDATA[String]]></Type>
<Dimension><![CDATA[]]></Dimension>
<Comment><![CDATA[]]></Comment>
</Variable>
<Variable>
<Name><![CDATA[cvalue]]></Name>
<Value><![CDATA[255]]></Value>
<Type><![CDATA[int]]></Type>
<Dimension><![CDATA[]]></Dimension>
<Comment><![CDATA[]]></Comment>
</Variable>
<Variable>
<Name><![CDATA[]]></Name>
<Value><![CDATA[]]></Value>
<Type><![CDATA[double]]></Type>
<Dimension><![CDATA[]]></Dimension>
<Comment><![CDATA[]]></Comment>
</Variable>
</Content>
</Osejs.Model.Variables.Page>
<Osejs.Model.Variables.Page>
<Type>VARIABLE_EDITOR</Type>
<Name>lookang</Name>
<Active>true</Active>
<Internal>false</Internal>
<Content>
<PageComment><![CDATA[]]></PageComment>
<Variable>
<Name><![CDATA[lencolor]]></Name>
<Value><![CDATA[]]></Value>
<Type><![CDATA[Object]]></Type>
<Dimension><![CDATA[]]></Dimension>
<Comment><![CDATA[]]></Comment>
</Variable>
<Variable>
<Name><![CDATA[backgroundcolor]]></Name>
<Value><![CDATA[]]></Value>
<Type><![CDATA[Object]]></Type>
<Dimension><![CDATA[]]></Dimension>
<Comment><![CDATA[]]></Comment>
</Variable>
<Variable>
<Name><![CDATA[textcolor]]></Name>
<Value><![CDATA[]]></Value>
<Type><![CDATA[Object]]></Type>
<Dimension><![CDATA[]]></Dimension>
<Comment><![CDATA[]]></Comment>
</Variable>
<Variable>
<Name><![CDATA[]]></Name>
<Value><![CDATA[]]></Value>
<Type><![CDATA[double]]></Type>
<Dimension><![CDATA[]]></Dimension>
<Comment><![CDATA[]]></Comment>
</Variable>
</Content>
</Osejs.Model.Variables.Page>
</Osejs.Model.Variables>
<Osejs.Model.Initialization>
<Osejs.Model.Initialization.Page>
<Type>CODE_EDITOR</Type>
<Name>Init Page</Name>
<Active>true</Active>
<Internal>false</Internal>
<Content>
<Comment><![CDATA[]]></Comment>
<Code><![CDATA[
_view.DrawingPanel.setAntialiasTextOn(true);
_view.DrawingPanel.setAntialiasShapeOn(true);

draglight();
  for(int i=0;i<n;i++){
   xp1[i]=p;yp1[i]=ly;
   block[i]=-1;
   stage[i]=0;
  }
   bcount=0;
  t=0.;
//blocked=false;



]]></Code>
</Content>
</Osejs.Model.Initialization.Page>
</Osejs.Model.Initialization>
<Osejs.Model.Evolution>
<Osejs.Model.Evolution.Page>
<Type>EVOLUTION_EDITOR</Type>
<Name>Evol Page 2</Name>
<Active>true</Active>
<Internal>false</Internal>
<Content>
<Comment><![CDATA[]]></Comment>
<Code><![CDATA[
t=t+dt;
]]></Code>
</Content>
</Osejs.Model.Evolution.Page>
</Osejs.Model.Evolution>
<Osejs.Model.Constraints>
<Osejs.Model.Constraints.Page>
<Type>CODE_EDITOR</Type>
<Name>Cons Page</Name>
<Active>true</Active>
<Internal>false</Internal>
<Content>
<Comment><![CDATA[]]></Comment>
<Code><![CDATA[
double vx=0,vy=0,v,x2,y2,ddt;
int count;
count=0;
if(t>dt)for(int i=0;i<n;i++){
 if(block[i]==1){//blocked 
   count++;
 }else if(xp1[i]<x){
   vx=dxp1[i]; vy=dyp1[i];
 }else if(xp1[i]<xmax){
   if(dxp2[i]<0){
   vx=-dxp2[i]; vy=-dyp2[i];
   }else{
    vx=dxp2[i]; vy=dyp2[i];
   }
 }else{// pass xmax
   vx=dxp1[i]; vy=dyp1[i];
   count++;
 }

  if(block[i]<1){//not blocked
    v=Math.sqrt(vx*vx+vy*vy);
    vxp=vx*c/v;
    vyp=vy*c/v;
    x2=xp1[i]+vxp*dt;
    y2=yp1[i]+vyp*dt;
    if((bx-xp1[i])*(bx-x2) <=0 ){// may be passing block
      ddt=(bx-xp1[i])/vxp;
      if( (y2-bh)*(y2+bh)>=0) {// blocked
        block[i]=1;
        x2=bx;
        y2=yp1[i]+vyp*ddt;
         count++;
         bcount++;
         blocked=true;
         cvalue=(int)(255.*(n-bcount)*(n-bcount)/n/n);
         clr=new java.awt.Color(0,0,cvalue,cvalue);
      }
    }else if((x-xp1[i])*(x-x2) <0 ){//passing lens
      ddt=(x-xp1[i])/vxp;
      x2=x;
      y2=yp1[i]+vyp*ddt; 
    }
      xp1[i]=x2;
      yp1[i]=y2;
 }
}
Ivalue=(int)(cvalue*1000./255.)/10.;
Itext=I_intensity+"="+Ivalue+"%";
if(count==n){
 if(autoy){
  ly+=ldy;
  if(ly>h){
   ly=h;
  ldy=-Math.abs(ldy); 
  }else if(ly<0){
   ly=0;
   ldy=Math.abs(ldy);
  }
 }
 _initialize();
}
]]></Code>
</Content>
</Osejs.Model.Constraints.Page>
<Osejs.Model.Constraints.Page>
<Type>CODE_EDITOR</Type>
<Name>lookang</Name>
<Active>true</Active>
<Internal>false</Internal>
<Content>
<Comment><![CDATA[]]></Comment>
<Code><![CDATA[
textcolor = new java.awt.Color(200,220,208); //green with transparent 100
backgroundcolor = new java.awt.Color(0,0,0);
lencolor = new java.awt.Color(0,255,255);
]]></Code>
</Content>
</Osejs.Model.Constraints.Page>
</Osejs.Model.Constraints>
<Osejs.Model.Library>
<Osejs.Model.Library.Page>
<Type>LIBRARY_EDITOR</Type>
<Name>playpause</Name>
<Active>true</Active>
<Internal>false</Internal>
<Content>
<Comment><![CDATA[]]></Comment>
<Code><![CDATA[
public void playpause () {
 if(label==l_play){
  label=l_pause;
  _play();
 }else{
  label=l_play;
  _pause();
 }
}
]]></Code>
</Content>
</Osejs.Model.Library.Page>
<Osejs.Model.Library.Page>
<Type>LIBRARY_EDITOR</Type>
<Name>chinese</Name>
<Active>true</Active>
<Internal>false</Internal>
<Content>
<Comment><![CDATA[]]></Comment>
<Code><![CDATA[
public void zh_tw () {
 l_play="¼½©ñ";
 l_reset="­«³]";
 l_pause="¼È°±";
 l_init="ªì©l¤Æ";
 l_msg="¾×¦í³¡¤À¥ú½u";
 l_focus="µJÂI";
 l_autoy="¦Û°Ê¤W¤U²¾°ÊÅã¥Ü¤£¦P¥ú·½¸ô®|";
 label=l_play;
 _initialize();
}
public void locale(String type){
 if(type.equals("zh_tw"))zh_tw();
}
]]></Code>
</Content>
</Osejs.Model.Library.Page>
<Osejs.Model.Library.Page>
<Type>LIBRARY_EDITOR</Type>
<Name>dragf</Name>
<Active>true</Active>
<Internal>false</Internal>
<Content>
<Comment><![CDATA[]]></Comment>
<Code><![CDATA[
public void dragf1 () {
  if(x1<x+size)x1=x+size;
  f=x1-x;
  x2=x-f;
  updateaction();
}
public void dragf2 () {
  if(x2>x-size)x2=x-size;
  f=x-x2;
  x1=x+f;
  updateaction();
}
public void draglight(){

 if(ly>h)ly=h;
 else if(ly<0)ly=0;
  updateaction();
}

]]></Code>
</Content>
</Osejs.Model.Library.Page>
<Osejs.Model.Library.Page>
<Type>LIBRARY_EDITOR</Type>
<Name>update</Name>
<Active>true</Active>
<Internal>false</Internal>
<Content>
<Comment><![CDATA[]]></Comment>
<Code><![CDATA[
public void updateaction () {
cvalue=255;
double dy=lh/n,lymin;
zero=0.;
x1=x+f;
x2=x-f;
if(f!=p)q=x+(x-p)*f/(x-p-f);
else q=1.e5;
h2=q/p*h;
lymin=-lh/2+dy/2-ly;
for(int i=0;i<n;i++){
  xp1[i]=p;
  yp1[i]=ly;
  dxp1[i]=x-p;
  dyp1[i]=lymin+i*dy;
  xp2[i]=q;
  yp2[i]=h2;
   dxp2[i]=x-q;
   dyp2[i]=dyp1[i]+ly-ly*h2/h;
  block[i]=-1;
  stage[i]=0;
}
bcount=0;
t=0;
clr=new java.awt.Color(0,0,255);
 _resetView();
}
]]></Code>
</Content>
</Osejs.Model.Library.Page>
<Osejs.Model.Library.Page>
<Type>LIBRARY_EDITOR</Type>
<Name>block</Name>
<Active>true</Active>
<Internal>false</Internal>
<Content>
<Comment><![CDATA[]]></Comment>
<Code><![CDATA[
public void block() {
 bh=xmax/10;
// if(_isPlaying())playpause();
 _initialize();
}
]]></Code>
</Content>
</Osejs.Model.Library.Page>
</Osejs.Model.Library>
<Osejs.Model.Elements>
</Osejs.Model.Elements>
</Osejs.Model>
<Osejs.View>
<Osejs.View.Creation>
<Osejs.View.Creation.Element>
<Expanded>true</Expanded>
<Type>Elements.Frame</Type>
<Property name="name">Frame</Property>
<Property name="_ejs_mainWindow">true</Property>
<Property name="title"><![CDATA[Frame]]></Property>
<Property name="layout"><![CDATA[border]]></Property>
<Property name="visible"><![CDATA[true]]></Property>
<Property name="location"><![CDATA["328,254"]]></Property>
<Property name="size"><![CDATA["684,355"]]></Property>
</Osejs.View.Creation.Element>
<Osejs.View.Creation.Element>
<Expanded>true</Expanded>
<Type>Elements.Panel</Type>
<Property name="name">Panel</Property>
<Property name="parent">Frame</Property>
<Property name="position">south</Property>
<Property name="layout"><![CDATA[grid:0,1,0,0]]></Property>
</Osejs.View.Creation.Element>
<Osejs.View.Creation.Element>
<Expanded>true</Expanded>
<Type>Elements.Panel</Type>
<Property name="name">Panel1</Property>
<Property name="parent">Panel</Property>
<Property name="position">south</Property>
<Property name="layout"><![CDATA[hbox]]></Property>
</Osejs.View.Creation.Element>
<Osejs.View.Creation.Element>
<Type>Elements.Button</Type>
<Property name="name">reset</Property>
<Property name="parent">Panel1</Property>
<Property name="image"><![CDATA["/org/opensourcephysics/resources/controls/images/reset.gif"]]></Property>
<Property name="action"><![CDATA[_reset()]]></Property>
</Osejs.View.Creation.Element>
<Osejs.View.Creation.Element>
<Type>Elements.Button</Type>
<Property name="name">initialize</Property>
<Property name="parent">Panel1</Property>
<Property name="image"><![CDATA["/org/opensourcephysics/resources/controls/images/initial.gif"]]></Property>
<Property name="action"><![CDATA[_initialize()]]></Property>
</Osejs.View.Creation.Element>
<Osejs.View.Creation.Element>
<Type>Elements.TwoStateButton</Type>
<Property name="name">twoStateButton</Property>
<Property name="parent">Panel1</Property>
<Property name="variable"><![CDATA[_isPaused]]></Property>
<Property name="imageOn"><![CDATA["/org/opensourcephysics/resources/controls/images/play.gif"]]></Property>
<Property name="actionOn"><![CDATA[_play()]]></Property>
<Property name="imageOff"><![CDATA["/org/opensourcephysics/resources/controls/images/pause.gif"]]></Property>
<Property name="actionOff"><![CDATA[_pause()]]></Property>
</Osejs.View.Creation.Element>
<Osejs.View.Creation.Element>
<Type>Elements.Button</Type>
<Property name="name">Hidepartofpath</Property>
<Property name="parent">Panel1</Property>
<Property name="text"><![CDATA[%l_msg%]]></Property>
<Property name="enabled"><![CDATA[!blocked]]></Property>
<Property name="action"><![CDATA[block()]]></Property>
</Osejs.View.Creation.Element>
<Osejs.View.Creation.Element>
<Type>Elements.CheckBox</Type>
<Property name="name">CheckBoxAUTO</Property>
<Property name="parent">Panel1</Property>
<Property name="variable"><![CDATA[autoy]]></Property>
<Property name="selected"><![CDATA[true]]></Property>
<Property name="text"><![CDATA[%l_autoy%]]></Property>
</Osejs.View.Creation.Element>
<Osejs.View.Creation.Element>
<Expanded>true</Expanded>
<Type>Elements.DrawingPanel</Type>
<Property name="name">DrawingPanel</Property>
<Property name="parent">Frame</Property>
<Property name="position">center</Property>
<Property name="autoscaleX"><![CDATA[false]]></Property>
<Property name="autoscaleY"><![CDATA[false]]></Property>
<Property name="minimumX"><![CDATA[xmin]]></Property>
<Property name="maximumX"><![CDATA[xmax]]></Property>
<Property name="minimumY"><![CDATA[ymin]]></Property>
<Property name="maximumY"><![CDATA[ymax]]></Property>
<Property name="square"><![CDATA[true]]></Property>
</Osejs.View.Creation.Element>
<Osejs.View.Creation.Element>
<Type>Elements.Particle</Type>
<Property name="name">objectp</Property>
<Property name="parent">DrawingPanel</Property>
<Property name="x"><![CDATA[p]]></Property>
<Property name="y"><![CDATA[zero]]></Property>
<Property name="sizex"><![CDATA[size2]]></Property>
<Property name="sizey"><![CDATA[size2]]></Property>
<Property name="enabled"><![CDATA[false]]></Property>
<Property name="dragaction"><![CDATA[updateaction()]]></Property>
</Osejs.View.Creation.Element>
<Osejs.View.Creation.Element>
<Type>Elements.Arrow</Type>
<Property name="name">image</Property>
<Property name="parent">DrawingPanel</Property>
<Property name="x"><![CDATA[q]]></Property>
<Property name="y"><![CDATA[zero]]></Property>
<Property name="sizex"><![CDATA[zero]]></Property>
<Property name="sizey"><![CDATA[h2]]></Property>
<Property name="enabledSecondary"><![CDATA[false]]></Property>
<Property name="enabled"><![CDATA[false]]></Property>
<Property name="color"><![CDATA[clr]]></Property>
<Property name="secondaryColor"><![CDATA[clr]]></Property>
<Property name="stroke"><![CDATA[size2]]></Property>
</Osejs.View.Creation.Element>
<Osejs.View.Creation.Element>
<Type>Elements.ArrowSet</Type>
<Property name="name">ray1</Property>
<Property name="parent">DrawingPanel</Property>
<Property name="elementnumber"><![CDATA[n]]></Property>
<Property name="x"><![CDATA[xp1]]></Property>
<Property name="y"><![CDATA[yp1]]></Property>
<Property name="sizex"><![CDATA[dxp1]]></Property>
<Property name="sizey"><![CDATA[dyp1]]></Property>
<Property name="visible"><![CDATA[false]]></Property>
<Property name="enabledSecondary"><![CDATA[false]]></Property>
<Property name="enabled"><![CDATA[false]]></Property>
<Property name="style"><![CDATA[SEGMENT]]></Property>
</Osejs.View.Creation.Element>
<Osejs.View.Creation.Element>
<Type>Elements.ArrowSet</Type>
<Property name="name">ray2</Property>
<Property name="parent">DrawingPanel</Property>
<Property name="elementnumber"><![CDATA[n]]></Property>
<Property name="x"><![CDATA[xp2]]></Property>
<Property name="y"><![CDATA[yp2]]></Property>
<Property name="sizex"><![CDATA[dxp2]]></Property>
<Property name="sizey"><![CDATA[dyp2]]></Property>
<Property name="visible"><![CDATA[false]]></Property>
<Property name="enabledSecondary"><![CDATA[false]]></Property>
<Property name="enabled"><![CDATA[false]]></Property>
<Property name="style"><![CDATA[SEGMENT]]></Property>
</Osejs.View.Creation.Element>
<Osejs.View.Creation.Element>
<Type>Elements.Particle</Type>
<Property name="name">light</Property>
<Property name="parent">DrawingPanel</Property>
<Property name="x"><![CDATA[p+0]]></Property>
<Property name="y"><![CDATA[ly]]></Property>
<Property name="sizex"><![CDATA[size]]></Property>
<Property name="sizey"><![CDATA[size]]></Property>
<Property name="enabled"><![CDATA[true]]></Property>
<Property name="dragaction"><![CDATA[draglight()]]></Property>
<Property name="style"><![CDATA[ELLIPSE]]></Property>
<Property name="secondaryColor"><![CDATA[0,0,255,128]]></Property>
<Property name="color"><![CDATA[0,0,255,128]]></Property>
</Osejs.View.Creation.Element>
<Osejs.View.Creation.Element>
<Type>Elements.ParticleSet</Type>
<Property name="name">ray</Property>
<Property name="parent">DrawingPanel</Property>
<Property name="elementnumber"><![CDATA[n]]></Property>
<Property name="x"><![CDATA[xp1]]></Property>
<Property name="y"><![CDATA[yp1]]></Property>
<Property name="sizex"><![CDATA[size4]]></Property>
<Property name="sizey"><![CDATA[size4]]></Property>
<Property name="enabled"><![CDATA[false]]></Property>
</Osejs.View.Creation.Element>
<Osejs.View.Creation.Element>
<Type>Elements.TraceSet</Type>
<Property name="name">TraceSet</Property>
<Property name="parent">DrawingPanel</Property>
<Property name="elementnumber"><![CDATA[n]]></Property>
<Property name="x"><![CDATA[xp1]]></Property>
<Property name="y"><![CDATA[yp1]]></Property>
<Property name="connected"><![CDATA[_isPlaying]]></Property>
<Property name="color"><![CDATA[0,0,255,128]]></Property>
</Osejs.View.Creation.Element>
<Osejs.View.Creation.Element>
<Type>Elements.Arrow</Type>
<Property name="name">object</Property>
<Property name="parent">DrawingPanel</Property>
<Property name="x"><![CDATA[p]]></Property>
<Property name="y"><![CDATA[zero]]></Property>
<Property name="sizex"><![CDATA[zero]]></Property>
<Property name="sizey"><![CDATA[h]]></Property>
<Property name="enabledSecondary"><![CDATA[true]]></Property>
<Property name="enabled"><![CDATA[true]]></Property>
<Property name="dragaction"><![CDATA[ldy=h/10;
updateaction();
draglight();]]></Property>
<Property name="color"><![CDATA[blue]]></Property>
<Property name="secondaryColor"><![CDATA[blue]]></Property>
<Property name="stroke"><![CDATA[size2]]></Property>
</Osejs.View.Creation.Element>
<Osejs.View.Creation.Element>
<Type>Elements.Particle</Type>
<Property name="name">blockp2</Property>
<Property name="parent">DrawingPanel</Property>
<Property name="x"><![CDATA[bx]]></Property>
<Property name="y"><![CDATA[bh]]></Property>
<Property name="sizex"><![CDATA[size2]]></Property>
<Property name="sizey"><![CDATA[size2]]></Property>
<Property name="enabled"><![CDATA[false]]></Property>
</Osejs.View.Creation.Element>
<Osejs.View.Creation.Element>
<Type>Elements.Arrow</Type>
<Property name="name">blocka</Property>
<Property name="parent">DrawingPanel</Property>
<Property name="x"><![CDATA[bx]]></Property>
<Property name="y"><![CDATA[bh]]></Property>
<Property name="sizex"><![CDATA[zero]]></Property>
<Property name="sizey"><![CDATA[ymax-bh]]></Property>
<Property name="enabledSecondary"><![CDATA[true]]></Property>
<Property name="enabled"><![CDATA[false]]></Property>
<Property name="dragaction"><![CDATA[blocked=false;
updateaction();]]></Property>
<Property name="style"><![CDATA[SEGMENT]]></Property>
<Property name="stroke"><![CDATA[stroke]]></Property>
</Osejs.View.Creation.Element>
<Osejs.View.Creation.Element>
<Type>Elements.Arrow</Type>
<Property name="name">blockb</Property>
<Property name="parent">DrawingPanel</Property>
<Property name="x"><![CDATA[bx]]></Property>
<Property name="y"><![CDATA[-bh]]></Property>
<Property name="sizex"><![CDATA[zero]]></Property>
<Property name="sizey"><![CDATA[ymin+bh]]></Property>
<Property name="enabledSecondary"><![CDATA[true]]></Property>
<Property name="enabled"><![CDATA[false]]></Property>
<Property name="dragaction"><![CDATA[updateaction()]]></Property>
<Property name="style"><![CDATA[SEGMENT]]></Property>
<Property name="stroke"><![CDATA[stroke]]></Property>
</Osejs.View.Creation.Element>
<Osejs.View.Creation.Element>
<Type>Elements.Particle</Type>
<Property name="name">imageL</Property>
<Property name="parent">DrawingPanel</Property>
<Property name="x"><![CDATA[q]]></Property>
<Property name="y"><![CDATA[ly*h2/h]]></Property>
<Property name="sizex"><![CDATA[size2]]></Property>
<Property name="sizey"><![CDATA[size2]]></Property>
<Property name="enabled"><![CDATA[false]]></Property>
<Property name="secondaryColor"><![CDATA[clr]]></Property>
<Property name="color"><![CDATA[clr]]></Property>
</Osejs.View.Creation.Element>
<Osejs.View.Creation.Element>
<Type>Elements.Text</Type>
<Property name="name">TextI</Property>
<Property name="parent">DrawingPanel</Property>
<Property name="x"><![CDATA[q]]></Property>
<Property name="y"><![CDATA[size]]></Property>
<Property name="enabled"><![CDATA[false]]></Property>
<Property name="text"><![CDATA[%Itext%]]></Property>
<Property name="elementposition"><![CDATA[SOUTH_WEST]]></Property>
</Osejs.View.Creation.Element>
<Osejs.View.Creation.Element>
<Expanded>true</Expanded>
<Type>Elements.Group2D</Type>
<Property name="name">lensgroup</Property>
<Property name="parent">DrawingPanel</Property>
</Osejs.View.Creation.Element>
<Osejs.View.Creation.Element>
<Type>Elements.Shape2D</Type>
<Property name="name">Lens</Property>
<Property name="parent">lensgroup</Property>
<Property name="x"><![CDATA[x]]></Property>
<Property name="y"><![CDATA[zero]]></Property>
<Property name="sizeX"><![CDATA[size]]></Property>
<Property name="sizeY"><![CDATA[lh]]></Property>
<Property name="enabledPosition"><![CDATA[true]]></Property>
<Property name="dragAction"><![CDATA[updateaction()]]></Property>
<Property name="fillColor"><![CDATA[lencolor]]></Property>
</Osejs.View.Creation.Element>
<Osejs.View.Creation.Element>
<Type>Elements.Segment2D</Type>
<Property name="name">principalaxishorizontalline2</Property>
<Property name="parent">lensgroup</Property>
<Property name="x"><![CDATA[xmin]]></Property>
<Property name="y"><![CDATA[zero]]></Property>
<Property name="sizeX"><![CDATA[xmax-xmin]]></Property>
<Property name="sizeY"><![CDATA[zero]]></Property>
<Property name="enabledSize"><![CDATA[false]]></Property>
<Property name="lineColor"><![CDATA[YELLOW]]></Property>
</Osejs.View.Creation.Element>
<Osejs.View.Creation.Element>
<Type>Elements.Shape2D</Type>
<Property name="name">focusl</Property>
<Property name="parent">lensgroup</Property>
<Property name="x"><![CDATA[x1]]></Property>
<Property name="y"><![CDATA[zero]]></Property>
<Property name="sizeX"><![CDATA[size2]]></Property>
<Property name="sizeY"><![CDATA[size2]]></Property>
<Property name="enabledPosition"><![CDATA[true]]></Property>
<Property name="dragAction"><![CDATA[dragf1()]]></Property>
<Property name="style"><![CDATA[WHEEL]]></Property>
<Property name="lineColor"><![CDATA[LIGHTGRAY]]></Property>
<Property name="fillColor"><![CDATA[WHITE]]></Property>
</Osejs.View.Creation.Element>
<Osejs.View.Creation.Element>
<Type>Elements.Shape2D</Type>
<Property name="name">focusr</Property>
<Property name="parent">lensgroup</Property>
<Property name="x"><![CDATA[x2]]></Property>
<Property name="y"><![CDATA[zero]]></Property>
<Property name="sizeX"><![CDATA[size2]]></Property>
<Property name="sizeY"><![CDATA[size2]]></Property>
<Property name="enabledPosition"><![CDATA[true]]></Property>
<Property name="dragAction"><![CDATA[dragf2()]]></Property>
<Property name="style"><![CDATA[WHEEL]]></Property>
<Property name="lineColor"><![CDATA[LIGHTGRAY]]></Property>
<Property name="fillColor"><![CDATA[WHITE]]></Property>
</Osejs.View.Creation.Element>
<Osejs.View.Creation.Element>
<Type>Elements.Text2D</Type>
<Property name="name">textF</Property>
<Property name="parent">lensgroup</Property>
<Property name="x"><![CDATA[x1]]></Property>
<Property name="y"><![CDATA[size/2]]></Property>
<Property name="pixelSize"><![CDATA[true]]></Property>
<Property name="enabledPosition"><![CDATA[false]]></Property>
<Property name="text"><![CDATA["F"]]></Property>
<Property name="font"><![CDATA[Arial,PLAIN,20]]></Property>
<Property name="elementposition"><![CDATA[SOUTH]]></Property>
<Property name="lineColor"><![CDATA[textcolor]]></Property>
</Osejs.View.Creation.Element>
<Osejs.View.Creation.Element>
<Type>Elements.Text2D</Type>
<Property name="name">textF2</Property>
<Property name="parent">lensgroup</Property>
<Property name="x"><![CDATA[x2]]></Property>
<Property name="y"><![CDATA[size/2]]></Property>
<Property name="sizeX"><![CDATA[size]]></Property>
<Property name="sizeY"><![CDATA[size]]></Property>
<Property name="pixelSize"><![CDATA[true]]></Property>
<Property name="enabledPosition"><![CDATA[false]]></Property>
<Property name="text"><![CDATA["F"]]></Property>
<Property name="font"><![CDATA[Arial,PLAIN,20]]></Property>
<Property name="elementposition"><![CDATA[SOUTH]]></Property>
<Property name="lineColor"><![CDATA[textcolor]]></Property>
</Osejs.View.Creation.Element>
<Osejs.View.Creation.Element>
<Type>Elements.Shape2D</Type>
<Property name="name">opticalcentre</Property>
<Property name="parent">lensgroup</Property>
<Property name="x"><![CDATA[x]]></Property>
<Property name="y"><![CDATA[zero]]></Property>
<Property name="sizeX"><![CDATA[size2]]></Property>
<Property name="sizeY"><![CDATA[size2]]></Property>
<Property name="enabledPosition"><![CDATA[false]]></Property>
<Property name="style"><![CDATA[WHEEL]]></Property>
<Property name="lineColor"><![CDATA[LIGHTGRAY]]></Property>
<Property name="fillColor"><![CDATA[BLACK]]></Property>
</Osejs.View.Creation.Element>
<Osejs.View.Creation.Element>
<Type>Elements.Text2D</Type>
<Property name="name">textc</Property>
<Property name="parent">lensgroup</Property>
<Property name="x"><![CDATA[x]]></Property>
<Property name="y"><![CDATA[zero]]></Property>
<Property name="sizeX"><![CDATA[size]]></Property>
<Property name="sizeY"><![CDATA[size]]></Property>
<Property name="pixelSize"><![CDATA[true]]></Property>
<Property name="enabledPosition"><![CDATA[false]]></Property>
<Property name="text"><![CDATA["c"]]></Property>
<Property name="font"><![CDATA[Arial,PLAIN,20]]></Property>
<Property name="elementposition"><![CDATA[SOUTH]]></Property>
<Property name="lineColor"><![CDATA[textcolor]]></Property>
</Osejs.View.Creation.Element>
</Osejs.View.Creation>
</Osejs.View>
<Osejs.HtmlView>
</Osejs.HtmlView>
</Osejs>
